[
  [
    [
      "Chain",
      [
        [ "Pools", 4, [ "Round_robin" ] ],
        [ "Offset", 0, [ "Bracket", [ 4, 0, 0 ] ] ],
        [ "Offset", 1, [ "Bracket", [ 1 ] ] ],
        [ "Offset", 2, [ "Bracket", [ 2, 0 ] ] ]
      ]
    ],
    {
      "samples": 7332,
      "sum": 25745.328987606637,
      "sum_squares": 112134.37685990849
    }
  ],
  [
    [
      "Chain",
      [
        [ "Pools", 4, [ "Round_robin" ] ],
        [ "Offset", 0, [ "Bracket", [ 4, 0, 0 ] ] ],
        [ "Offset", 1, [ "Bracket", [ 1 ] ] ],
        [ "Offset", 2, [ "Bracket", [ 4, 2, 0, 0 ] ] ]
      ]
    ],
    {
      "samples": 15336,
      "sum": 53536.756319377324,
      "sum_squares": 232126.6857649586
    }
  ],
  [
    [
      "Chain",
      [
        [ "Pools", 4, [ "Round_robin" ] ],
        [ "Offset", 0, [ "Bracket", [ 4, 0, 0 ] ] ],
        [ "Offset", 1, [ "Bracket", [ 1 ] ] ],
        [ "Offset", 2, [ "Bracket", [ 8, 0, 2, 0, 0 ] ] ]
      ]
    ],
    {
      "samples": 11453,
      "sum": 39955.64633680624,
      "sum_squares": 173281.61111636678
    }
  ],
  [
    [
      "Chain",
      [
        [ "Pools", 4, [ "Round_robin" ] ],
        [ "Offset", 0, [ "Bracket", [ 4, 0, 0 ] ] ],
        [ "Offset", 1, [ "Bracket", [ 1 ] ] ],
        [ "Offset", 2, [ "Bracket", [ 4, 6, 0, 0, 0 ] ] ]
      ]
    ],
    {
      "samples": 8882,
      "sum": 31139.42919887397,
      "sum_squares": 135490.26584147746
    }
  ],
  [
    [
      "Chain",
      [
        [ "Pools", 4, [ "Round_robin" ] ],
        [ "Offset", 0, [ "Bracket", [ 4, 0, 0 ] ] ],
        [ "Offset", 1, [ "Bracket", [ 2, 1, 0 ] ] ],
        [ "Offset", 2, [ "Bracket", [ 1 ] ] ]
      ]
    ],
    {
      "samples": 7695,
      "sum": 27052.518228997833,
      "sum_squares": 118343.03453523286
    }
  ],
  [
    [
      "Chain",
      [
        [ "Pools", 4, [ "Round_robin" ] ],
        [ "Offset", 0, [ "Bracket", [ 4, 0, 0 ] ] ],
        [ "Offset", 1, [ "Bracket", [ 2, 1, 0 ] ] ],
        [ "Offset", 2, [ "Bracket", [ 2, 0 ] ] ]
      ]
    ],
    {
      "samples": 15119,
      "sum": 52644.12026030013,
      "sum_squares": 227793.64404617407
    }
  ],
  [
    [
      "Chain",
      [
        [ "Pools", 4, [ "Round_robin" ] ],
        [ "Offset", 0, [ "Bracket", [ 4, 0, 0 ] ] ],
        [ "Offset", 1, [ "Bracket", [ 2, 1, 0 ] ] ],
        [ "Offset", 2, [ "Bracket", [ 4, 0, 1, 1, 0 ] ] ]
      ]
    ],
    {
      "samples": 8158,
      "sum": 28579.240829699695,
      "sum_squares": 124404.05514939268
    }
  ],
  [
    [
      "Chain",
      [
        [ "Pools", 4, [ "Round_robin" ] ],
        [ "Offset", 0, [ "Bracket", [ 4, 0, 0 ] ] ],
        [ "Offset", 1, [ "Bracket", [ 2, 1, 0 ] ] ],
        [ "Offset", 2, [ "Bracket", [ 8, 0, 0, 1, 1, 0 ] ] ]
      ]
    ],
    {
      "samples": 5991,
      "sum": 21246.008538974133,
      "sum_squares": 93051.866782264
    }
  ],
  [
    [
      "Chain",
      [
        [ "Pools", 4, [ "Round_robin" ] ],
        [ "Offset", 0, [ "Bracket", [ 4, 0, 0 ] ] ],
        [ "Offset", 1, [ "Bracket", [ 2, 1, 0 ] ] ],
        [ "Offset", 2, [ "Bracket", [ 4, 4, 1, 0, 1, 0 ] ] ]
      ]
    ],
    {
      "samples": 14949,
      "sum": 52144.121315499884,
      "sum_squares": 225979.6920389895
    }
  ],
  [
    [
      "Chain",
      [
        [ "Pools", 4, [ "Round_robin" ] ],
        [ "Offset", 0, [ "Bracket", [ 4, 0, 0 ] ] ],
        [ "Offset", 1, [ "Bracket", [ 2, 1, 0 ] ] ],
        [ "Offset", 2, [ "Bracket", [ 4, 2, 0, 0 ] ] ]
      ]
    ],
    {
      "samples": 7797,
      "sum": 27461.88750809536,
      "sum_squares": 119992.57787819844
    }
  ],
  [
    [
      "Chain",
      [
        [ "Pools", 4, [ "Round_robin" ] ],
        [ "Offset", 0, [ "Bracket", [ 4, 0, 0 ] ] ],
        [ "Offset", 1, [ "Bracket", [ 2, 1, 0 ] ] ],
        [ "Offset", 2, [ "Bracket", [ 8, 0, 2, 0, 0 ] ] ]
      ]
    ],
    {
      "samples": 20667,
      "sum": 71920.21042194974,
      "sum_squares": 310898.377421626
    }
  ],
  [
    [
      "Chain",
      [
        [ "Pools", 4, [ "Round_robin" ] ],
        [ "Offset", 0, [ "Bracket", [ 4, 0, 0 ] ] ],
        [ "Offset", 1, [ "Bracket", [ 2, 1, 0 ] ] ],
        [ "Offset", 2, [ "Bracket", [ 4, 0, 5, 1, 0, 0 ] ] ]
      ]
    ],
    {
      "samples": 17046,
      "sum": 59153.93555401789,
      "sum_squares": 255261.58169768009
    }
  ],
  [
    [
      "Chain",
      [
        [ "Pools", 4, [ "Round_robin" ] ],
        [ "Offset", 0, [ "Bracket", [ 4, 0, 0 ] ] ],
        [ "Offset", 1, [ "Bracket", [ 4, 2, 0, 1, 0 ] ] ],
        [ "Offset", 2, [ "Bracket", [ 1 ] ] ]
      ]
    ],
    {
      "samples": 11534,
      "sum": 40280.31806955,
      "sum_squares": 174626.8104408655
    }
  ],
  [
    [
      "Chain",
      [
        [ "Pools", 4, [ "Round_robin" ] ],
        [ "Offset", 0, [ "Bracket", [ 4, 0, 0 ] ] ],
        [ "Offset", 1, [ "Bracket", [ 4, 2, 0, 1, 0 ] ] ],
        [ "Offset", 2, [ "Bracket", [ 2, 0 ] ] ]
      ]
    ],
    {
      "samples": 12936,
      "sum": 45291.545325979416,
      "sum_squares": 196794.07502583673
    }
  ],
  [
    [
      "Chain",
      [
        [ "Pools", 4, [ "Round_robin" ] ],
        [ "Offset", 0, [ "Bracket", [ 4, 0, 0 ] ] ],
        [ "Offset", 1, [ "Bracket", [ 4, 2, 0, 1, 0 ] ] ],
        [ "Offset", 2, [ "Bracket", [ 2, 1, 1, 0 ] ] ]
      ]
    ],
    {
      "samples": 11245,
      "sum": 39247.20626150519,
      "sum_squares": 170311.9087191251
    }
  ],
  [
    [
      "Chain",
      [
        [ "Pools", 4, [ "Round_robin" ] ],
        [ "Offset", 0, [ "Bracket", [ 4, 0, 0 ] ] ],
        [ "Offset", 1, [ "Bracket", [ 8, 0, 2, 0, 1, 0 ] ] ],
        [ "Offset", 2, [ "Bracket", [ 1 ] ] ]
      ]
    ],
    {
      "samples": 11450,
      "sum": 40119.369745835786,
      "sum_squares": 174656.61877175688
    }
  ],
  [
    [
      "Chain",
      [
        [ "Pools", 4, [ "Round_robin" ] ],
        [ "Offset", 0, [ "Bracket", [ 4, 0, 0 ] ] ],
        [ "Offset", 1, [ "Bracket", [ 4, 6, 0, 0, 1, 0 ] ] ],
        [ "Offset", 2, [ "Bracket", [ 1 ] ] ]
      ]
    ],
    {
      "samples": 8775,
      "sum": 30750.64121401494,
      "sum_squares": 134752.27988734146
    }
  ],
  [
    [
      "Chain",
      [
        [ "Pools", 4, [ "Round_robin" ] ],
        [ "Offset", 0, [ "Bracket", [ 4, 0, 0 ] ] ],
        [ "Offset", 1, [ "Bracket", [ 4, 0, 3, 0, 0 ] ] ],
        [ "Offset", 2, [ "Bracket", [ 1 ] ] ]
      ]
    ],
    {
      "samples": 3558,
      "sum": 12596.130005192656,
      "sum_squares": 55291.731913028285
    }
  ],
  [
    [
      "Chain",
      [
        [ "Pools", 4, [ "Round_robin" ] ],
        [ "Offset", 0, [ "Bracket", [ 4, 0, 0 ] ] ],
        [ "Offset", 1, [ "Bracket", [ 4, 0, 3, 0, 0 ] ] ],
        [ "Offset", 2, [ "Bracket", [ 2, 1, 0 ] ] ]
      ]
    ],
    {
      "samples": 12102,
      "sum": 42258.50983049949,
      "sum_squares": 182768.1880786146
    }
  ],
  [
    [
      "Chain",
      [
        [ "Pools", 4, [ "Round_robin" ] ],
        [ "Offset", 0, [ "Bracket", [ 4, 0, 0 ] ] ],
        [ "Offset", 1, [ "Bracket", [ 8, 0, 0, 3, 0, 0 ] ] ],
        [ "Offset", 2, [ "Bracket", [ 1 ] ] ]
      ]
    ],
    {
      "samples": 10987,
      "sum": 38418.08763206961,
      "sum_squares": 166181.59827489557
    }
  ],
  [
    [
      "Chain",
      [
        [ "Pools", 4, [ "Round_robin" ] ],
        [ "Offset", 0, [ "Bracket", [ 4, 0, 0 ] ] ],
        [ "Offset", 1, [ "Bracket", [ 6, 1, 0, 0 ] ] ],
        [ "Offset", 2, [ "Bracket", [ 1 ] ] ]
      ]
    ],
    {
      "samples": 8304,
      "sum": 29227.069172934764,
      "sum_squares": 128010.52851550019
    }
  ],
  [
    [
      "Chain",
      [
        [ "Pools", 4, [ "Round_robin" ] ],
        [ "Offset", 0, [ "Bracket", [ 4, 0, 0 ] ] ],
        [ "Offset", 1, [ "Bracket", [ 6, 1, 0, 0 ] ] ],
        [ "Offset", 2, [ "Bracket", [ 2, 1, 0 ] ] ]
      ]
    ],
    {
      "samples": 13372,
      "sum": 46618.51529698855,
      "sum_squares": 202220.84946517894
    }
  ],
  [
    [
      "Chain",
      [
        [ "Pools", 4, [ "Round_robin" ] ],
        [ "Offset", 0, [ "Bracket", [ 4, 0, 0 ] ] ],
        [ "Offset", 1, [ "Bracket", [ 8, 2, 1, 0, 0 ] ] ],
        [ "Offset", 2, [ "Bracket", [ 1 ] ] ]
      ]
    ],
    {
      "samples": 10971,
      "sum": 38510.541053221525,
      "sum_squares": 167974.71525420982
    }
  ],
  [
    [
      "Chain",
      [
        [ "Pools", 4, [ "Round_robin" ] ],
        [ "Offset", 0, [ "Bracket", [ 4, 0, 0 ] ] ],
        [ "Offset", 1, [ "Bracket", [ 8, 2, 1, 0, 0 ] ] ],
        [ "Offset", 2, [ "Bracket", [ 2, 1, 0 ] ] ]
      ]
    ],
    {
      "samples": 6320,
      "sum": 22276.673907079945,
      "sum_squares": 97800.51608448653
    }
  ],
  [
    [
      "Chain",
      [
        [ "Pools", 4, [ "Round_robin" ] ],
        [ "Offset", 0, [ "Bracket", [ 4, 0, 0 ] ] ],
        [ "Offset", 1, [ "Bracket", [ 4, 0, 7, 0, 0, 0 ] ] ],
        [ "Offset", 2, [ "Bracket", [ 1 ] ] ]
      ]
    ],
    {
      "samples": 12288,
      "sum": 42933.0229467585,
      "sum_squares": 186130.4326469117
    }
  ],
  [
    [
      "Chain",
      [
        [ "Pools", 4, [ "Round_robin" ] ],
        [ "Offset", 0, [ "Bracket", [ 8, 0, 0, 0 ] ] ],
        [ "Offset", 1, [ "Bracket", [ 1 ] ] ],
        [ "Offset", 2, [ "Bracket", [ 2, 0 ] ] ]
      ]
    ],
    {
      "samples": 7727,
      "sum": 27245.634192684432,
      "sum_squares": 119198.46414655002
    }
  ],
  [
    [
      "Chain",
      [
        [ "Pools", 4, [ "Round_robin" ] ],
        [ "Offset", 0, [ "Bracket", [ 8, 0, 0, 0 ] ] ],
        [ "Offset", 1, [ "Bracket", [ 1 ] ] ],
        [ "Offset", 2, [ "Bracket", [ 4, 2, 0, 0 ] ] ]
      ]
    ],
    {
      "samples": 8862,
      "sum": 31179.63414720196,
      "sum_squares": 136478.23386860656
    }
  ],
  [
    [
      "Chain",
      [
        [ "Pools", 4, [ "Round_robin" ] ],
        [ "Offset", 0, [ "Bracket", [ 8, 0, 0, 0 ] ] ],
        [ "Offset", 1, [ "Bracket", [ 1 ] ] ],
        [ "Offset", 2, [ "Bracket", [ 8, 0, 2, 0, 0 ] ] ]
      ]
    ],
    {
      "samples": 7119,
      "sum": 24981.784710594515,
      "sum_squares": 108686.56293403267
    }
  ],
  [
    [
      "Chain",
      [
        [ "Pools", 4, [ "Round_robin" ] ],
        [ "Offset", 0, [ "Bracket", [ 8, 0, 0, 0 ] ] ],
        [ "Offset", 1, [ "Bracket", [ 1 ] ] ],
        [ "Offset", 2, [ "Bracket", [ 4, 6, 0, 0, 0 ] ] ]
      ]
    ],
    {
      "samples": 13226,
      "sum": 46269.060270464055,
      "sum_squares": 201285.79724707836
    }
  ],
  [
    [
      "Chain",
      [
        [ "Pools", 4, [ "Round_robin" ] ],
        [ "Offset", 0, [ "Bracket", [ 8, 0, 0, 0 ] ] ],
        [ "Offset", 1, [ "Bracket", [ 2, 1, 0 ] ] ],
        [ "Offset", 2, [ "Bracket", [ 1 ] ] ]
      ]
    ],
    {
      "samples": 9644,
      "sum": 33876.97043316344,
      "sum_squares": 148544.68317178218
    }
  ],
  [
    [
      "Chain",
      [
        [ "Pools", 4, [ "Round_robin" ] ],
        [ "Offset", 0, [ "Bracket", [ 8, 0, 0, 0 ] ] ],
        [ "Offset", 1, [ "Bracket", [ 2, 1, 0 ] ] ],
        [ "Offset", 2, [ "Bracket", [ 2, 0 ] ] ]
      ]
    ],
    {
      "samples": 11521,
      "sum": 40198.257310928304,
      "sum_squares": 174287.18164114575
    }
  ],
  [
    [
      "Chain",
      [
        [ "Pools", 4, [ "Round_robin" ] ],
        [ "Offset", 0, [ "Bracket", [ 8, 0, 0, 0 ] ] ],
        [ "Offset", 1, [ "Bracket", [ 2, 1, 0 ] ] ],
        [ "Offset", 2, [ "Bracket", [ 4, 0, 1, 1, 0 ] ] ]
      ]
    ],
    {
      "samples": 7176,
      "sum": 25314.90222648867,
      "sum_squares": 110951.9155190025
    }
  ],
  [
    [
      "Chain",
      [
        [ "Pools", 4, [ "Round_robin" ] ],
        [ "Offset", 0, [ "Bracket", [ 8, 0, 0, 0 ] ] ],
        [ "Offset", 1, [ "Bracket", [ 4, 2, 0, 1, 0 ] ] ],
        [ "Offset", 2, [ "Bracket", [ 1 ] ] ]
      ]
    ],
    {
      "samples": 12591,
      "sum": 43942.834339212095,
      "sum_squares": 190184.42655832137
    }
  ],
  [
    [
      "Chain",
      [
        [ "Pools", 4, [ "Round_robin" ] ],
        [ "Offset", 0, [ "Bracket", [ 8, 0, 0, 0 ] ] ],
        [ "Offset", 1, [ "Bracket", [ 4, 0, 3, 0, 0 ] ] ],
        [ "Offset", 2, [ "Bracket", [ 1 ] ] ]
      ]
    ],
    {
      "samples": 8022,
      "sum": 28140.7942441351,
      "sum_squares": 122370.5365725306
    }
  ],
  [
    [
      "Chain",
      [
        [ "Pools", 4, [ "Round_robin" ] ],
        [ "Offset", 0, [ "Bracket", [ 8, 0, 0, 0 ] ] ],
        [ "Offset", 1, [ "Bracket", [ 6, 1, 0, 0 ] ] ],
        [ "Offset", 2, [ "Bracket", [ 1 ] ] ]
      ]
    ],
    {
      "samples": 4096,
      "sum": 14488.98770035501,
      "sum_squares": 63391.051773445215
    }
  ],
  [
    [
      "Chain",
      [
        [ "Pools", 4, [ "Round_robin" ] ],
        [ "Offset", 0, [ "Bracket", [ 8, 0, 0, 0 ] ] ],
        [ "Offset", 1, [ "Bracket", [ 8, 2, 1, 0, 0 ] ] ],
        [ "Offset", 2, [ "Bracket", [ 1 ] ] ]
      ]
    ],
    {
      "samples": 9260,
      "sum": 32305.955455662563,
      "sum_squares": 140059.48978744814
    }
  ],
  [
    [
      "Chain",
      [
        [ "Pools", 4, [ "Round_robin" ] ],
        [ "Offset", 0, [ "Bracket", [ 8, 4, 0, 0, 0 ] ] ],
        [ "Offset", 1, [ "Bracket", [ 1 ] ] ],
        [ "Offset", 2, [ "Bracket", [ 2, 0 ] ] ]
      ]
    ],
    {
      "samples": 6680,
      "sum": 23525.48306895729,
      "sum_squares": 103022.76700237358
    }
  ],
  [
    [
      "Chain",
      [
        [ "Pools", 4, [ "Round_robin" ] ],
        [ "Offset", 0, [ "Bracket", [ 8, 4, 0, 0, 0 ] ] ],
        [ "Offset", 1, [ "Bracket", [ 1 ] ] ],
        [ "Offset", 2, [ "Bracket", [ 4, 2, 0, 0 ] ] ]
      ]
    ],
    {
      "samples": 17609,
      "sum": 61276.46112570072,
      "sum_squares": 265070.45746480074
    }
  ],
  [
    [
      "Chain",
      [
        [ "Pools", 4, [ "Round_robin" ] ],
        [ "Offset", 0, [ "Bracket", [ 8, 4, 0, 0, 0 ] ] ],
        [ "Offset", 1, [ "Bracket", [ 2, 1, 0 ] ] ],
        [ "Offset", 2, [ "Bracket", [ 1 ] ] ]
      ]
    ],
    {
      "samples": 10736,
      "sum": 37520.809661264335,
      "sum_squares": 163137.38803332357
    }
  ],
  [
    [
      "Chain",
      [
        [ "Pools", 2, [ "Round_robin" ] ],
        [ "Offset", 0, [ "Bracket", [ 2, 0 ] ] ],
        [ "Offset", 1, [ "Bracket", [ 1 ] ] ],
        [ "Offset", 2, [ "Bracket", [ 2, 0 ] ] ]
      ]
    ],
    {
      "samples": 7203,
      "sum": 25170.072116101666,
      "sum_squares": 108996.78428013893
    }
  ],
  [
    [
      "Chain",
      [
        [ "Pools", 2, [ "Round_robin" ] ],
        [ "Offset", 0, [ "Bracket", [ 2, 0 ] ] ],
        [ "Offset", 1, [ "Bracket", [ 1 ] ] ],
        [ "Offset", 2, [ "Bracket", [ 4, 0, 0 ] ] ]
      ]
    ],
    {
      "samples": 13224,
      "sum": 46041.44658303225,
      "sum_squares": 199288.53823153538
    }
  ],
  [
    [
      "Chain",
      [
        [ "Pools", 2, [ "Round_robin" ] ],
        [ "Offset", 0, [ "Bracket", [ 2, 0 ] ] ],
        [ "Offset", 1, [ "Bracket", [ 2, 1, 0 ] ] ],
        [ "Offset", 2, [ "Bracket", [ 1 ] ] ]
      ]
    ],
    {
      "samples": 3867,
      "sum": 13705.920726327864,
      "sum_squares": 60388.835555565805
    }
  ],
  [
    [
      "Chain",
      [
        [ "Pools", 2, [ "Round_robin" ] ],
        [ "Offset", 0, [ "Bracket", [ 4, 0, 0 ] ] ],
        [ "Offset", 1, [ "Bracket", [ 1 ] ] ],
        [ "Offset", 2, [ "Bracket", [ 2, 0 ] ] ]
      ]
    ],
    {
      "samples": 10083,
      "sum": 35257.55994189574,
      "sum_squares": 152573.09102926168
    }
  ]
]