[
  [
    [
      "Grid",
      [
        [ [ 1, 3 ], [ 1, 4 ], [ 1, 4 ], [ 0, 0 ], [ 0, 0 ] ],
        [ [ 3, 5 ], [ 1, 4 ], [ 1, 5 ], [ 0, 0 ] ],
        [ [ 3, 5 ], [ 1, 4 ], [ 1, 5 ], [ 0, 0 ] ],
        [ [ 3, 5 ], [ 1, 4 ], [ 1, 5 ], [ 0, 0 ] ],
        [ [ 3, 5 ], [ 1, 4 ], [ 1, 5 ], [ 0, 0 ] ]
      ]
    ],
    {
      "samples": 2300000,
      "sum": 909725.4489884737,
      "sum_squares": 956428.2274063741
    }
  ],
  [
    [
      "Chain",
      [
        [ "Pools", 5, [ "Round_robin" ] ],
        [ "Offset", 1, [ "Bracket", [ 4, 0, 0 ] ] ],
        [ "Bracket", [ 4, 8, 3, 0, 0, 0 ] ]
      ]
    ],
    {
      "samples": 600000,
      "sum": 237096.49390413606,
      "sum_squares": 248918.8263394904
    }
  ],
  [
    [
      "Chain",
      [ [ "Pools", 4, [ "Round_robin" ] ], [ "Bracket", [ 8, 4, 0, 0, 0 ] ] ]
    ],
    {
      "samples": 400000,
      "sum": 158500.29513673755,
      "sum_squares": 166989.220296534
    }
  ]
]